__init__.py
RandomChar/Generator.py
RandomChar/__init__.py
randomchar-0.0.1.dist-info/licenses/LICENSE
randomchar-0.0.1.dist-info/METADATA
randomchar-0.0.1.dist-info/WHEEL
randomchar-0.0.1.dist-info/top_level.txt
randomchar-0.0.1.dist-info/RECORD
