Metadata-Version: 2.4
Name: randomchar
Version: 0.0.1
Summary: Generating a random string
Author-email: Chiron <example@example.com>
License-Expression: MIT
Project-URL: Homepage, https://github.com/DevChiron/RandomChar
Project-URL: Issues, https://github.com/DevChiron/RandomChar/issues
Classifier: Programming Language :: Python :: 3
Requires-Python: >=3.9
License-File: LICENSE
Dynamic: license-file
